blog/__init__.py
blog/adminforms.py
blog/adminx.py
blog/apis.py
blog/apps.py
blog/models.py
blog/rss.py
blog/serializers.py
blog/sitemap.py
blog/tests.py
blog/views.py
blog/middleware/__init__.py
blog/middleware/user_id.py
blog/migrations/0001_initial.py
blog/migrations/0002_auto_20180310_1505.py
blog/migrations/0003_auto_20180325_1737.py
blog/migrations/0004_post_content_html.py
blog/migrations/0005_auto_20180502_1730.py
blog/migrations/0006_auto_20191104_0943.py
blog/migrations/0007_auto_20191106_1351.py
blog/migrations/0008_auto_20191110_2200.py
blog/migrations/0009_auto_20191110_2238.py
blog/migrations/0010_auto_20191110_2243.py
blog/migrations/0011_auto_20191112_1353.py
blog/migrations/0012_post_task_category.py
blog/migrations/0013_auto_20191112_1419.py
blog/migrations/0014_auto_20191112_1422.py
blog/migrations/0015_remove_post_task_category.py
blog/migrations/0016_post_task_category.py
blog/migrations/0017_auto_20191112_1431.py
blog/migrations/0018_remove_post_task_category.py
blog/migrations/0019_auto_20191205_1512.py
blog/migrations/__init__.py
catchtask/__init__.py
catchtask/admin.py
catchtask/apps.py
catchtask/models.py
catchtask/tests.py
catchtask/urls.py
catchtask/views.py
catchtask/migrations/__init__.py
comment/__init__.py
comment/adminx.py
comment/apps.py
comment/forms.py
comment/models.py
comment/tests.py
comment/views.py
comment/migrations/0001_initial.py
comment/migrations/0002_auto_20180410_1922.py
comment/migrations/0003_auto_20191108_1103.py
comment/migrations/__init__.py
comment/templatetags/__init__.py
comment/templatetags/comment_block.py
config/__init__.py
config/adminx.py
config/apps.py
config/models.py
config/tests.py
config/views.py
config/migrations/0001_initial.py
config/migrations/0002_auto_20180410_1922.py
config/migrations/0003_auto_20191104_0943.py
config/migrations/0004_auto_20191106_1351.py
config/migrations/__init__.py
extra_apps/__init__.py
extra_apps/xadmin/__init__.py
extra_apps/xadmin/adminx.py
extra_apps/xadmin/apps.py
typeidea_czz-0.15.dist-info/METADATA
typeidea_czz-0.15.dist-info/WHEEL
typeidea_czz-0.15.dist-info/entry_points.txt
typeidea_czz-0.15.dist-info/top_level.txt
typeidea_czz-0.15.dist-info/RECORD
