Metadata-Version: 2.1
Name: typeidea-czz
Version: 0.15
Summary: Sync Sys base on 
Home-page: https://www.czz.com
Author: czz
Author-email: jsmyxn@163.com
License: MIT
Platform: UNKNOWN
Classifier: Development Status :: 3 - Alpha
Classifier: Intended Audience :: Developers
Classifier: Topic :: Software Development :: Libraries
Classifier: License :: OSI Approved :: MIT License
Classifier: Programming Language :: Python :: 3.7
Requires-Dist: django (~=2.2.6)
Requires-Dist: gunicorn (==19.8.1)
Requires-Dist: supervisor (==4.0.0.0)
Requires-Dist: xadmin (==0.6.1)
Requires-Dist: mysqlclient (==1.4.6)
Requires-Dist: django-ckeditor (==5.4.0)
Requires-Dist: django-rest-framework (==0.1.0)
Requires-Dist: django-redis (==4.8.0)
Requires-Dist: django-autocomplete-light (==3.2.10)
Requires-Dist: mistune (==0.8.3)
Requires-Dist: coreapi (==2.3.3)
Requires-Dist: django-debug-toolbar (==1.9.1)
Requires-Dist: django-silk (==2.0.0)
Requires-Dist: pympler (==0.8)
Requires-Dist: captcha (==0.3)
Requires-Dist: future (==0.18.2)
Requires-Dist: django-import-export (==2.0)
Requires-Dist: django-simple-captcha (==0.5.12)
Requires-Dist: pyecharts (==1.6.0)
Provides-Extra: ipython
Requires-Dist: ipython (==6.2.1) ; extra == 'ipython'
